full_adder_1_bit/full_adder.v
//Full adder using structural modeling
module full_adder (
    input a,b,cin,
    output sum,carry
);

wire w1,w2,w3,w4;       //Internal connections

xor(w1,a,b);
xor(sum,w1,cin);        //Sum output

and(w2,a,b);
and(w3,b,cin);
and(w4,cin,a);

or(carry,w2,w3,w4);     //carry output

endmodule

full_adder_1_bit/full_adder_tb.v
`timescale 1ns / 1ns

`include "full_adder.v"


module full_adder_tb;


reg a;
reg b;
reg cin;

wire sum;
wire carry;

full_adder uut (a,b,cin,sum,carry);

initial begin
	$dumpfile("full_adder.vcd");
	$dumpvars(0, full_adder_tb);
	a = 0; b = 0; cin = 0;
	#10
	a = 0; b = 0; cin = 1;
	#10
	a = 0; b = 1; cin = 0;
	#10
	a = 0; b = 1; cin = 1;
	#10
	a = 1; b = 0; cin = 0;
	#10
	a = 1; b = 0; cin = 1;
	#10
	a = 1; b = 1; cin = 0;
	#10
	a = 1; b = 1; cin = 1;
	#10
	$display("test complete!");
end
               
endmodule

full_adder_1_bit/full_adder.vcd
$date
	Fri Sep  6 13:32:36 2024
$end
$version
	Icarus Verilog
$end
$timescale
	1ns
$end
$scope module full_adder_tb $end
$var wire 1 ! sum $end
$var wire 1 " carry $end
$var reg 1 # a $end
$var reg 1 $ b $end
$var reg 1 % cin $end
$scope module uut $end
$var wire 1 # a $end
$var wire 1 $ b $end
$var wire 1 " carry $end
$var wire 1 % cin $end
$var wire 1 ! sum $end
$var wire 1 & w1 $end
$var wire 1 ' w2 $end
$var wire 1 ( w3 $end
$var wire 1 ) w4 $end
$upscope $end
$upscope $end
$enddefinitions $end
$comment Show the parameter values. $end
$dumpall
$end
#0
$dumpvars
0)
0(
0'
0&
0%
0$
0#
0"
0!
$end
#10
1!
1%
#20
1&
0%
1$
#30
1"
0!
1(
1%
#40
0"
1!
0(
0%
0$
1#
#50
1"
0!
1)
1%
#60
0)
0&
1'
0%
1$
#70
1!
1(
1)
1%
