multiplexer/multiplexer.v
module multiplexer(I0, I1, I2, I3, I4, I5, I6, I7, S0, S1, S2, O0);

	input I0, I1, I2, I3, I4, I5, I6, I7, S0, S1, S2;
	output O0;

	wire W0, W1, W2, W3, W4, W5, W6, W7;

	and(W0, I0, ~S0, ~S1, ~S2);
	and(W1, I1, ~S0, ~S1, S2);
	and(W2, I2, ~S0, S1, ~S2);
	and(W3, I3, ~S0, S1, S2);
	and(W4, I4, S0, ~S1, ~S2);
	and(W5, I5, S0, ~S1, S2);
	and(W6, I6, S0, S1, ~S2);
	and(W7, I7, S0, S1, S2);
	
	or(O0, W0, W1, W2, W3, W4, W5, W6, W7);

endmodule

multiplexer/multiplexer_tb.v
`timescale 1ns / 1ns

`include "multiplexer.v"


module multiplexer_tb;

reg I0, I1, I2, I3, I4, I5, I6, I7, S0, S1, S2;

wire O0;

multiplexer uut(I0, I1, I2, I3, I4, I5, I6, I7, S0, S1, S2, O0);

initial begin
	$dumpfile("multiplexer.vcd");
	$dumpvars(0, multiplexer_tb);
	
    I0 = 1; I1 = 0; I2 = 0; I3 = 0; I4 = 0; I5 = 0; I6 = 0; I7 = 0;
    S0 = 0; S1 = 0; S2 = 0;
    #1
    S0 = 0; S1 = 0; S2 = 1;
    #1
    S0 = 0; S1 = 1; S2 = 0;
    #1
    S0 = 0; S1 = 1; S2 = 1;
    #1
    S0 = 1; S1 = 0; S2 = 0;
    #1
    S0 = 1; S1 = 0; S2 = 1;
    #1
    S0 = 1; S1 = 1; S2 = 0;
    #1
    S0 = 1; S1 = 1; S2 = 1;
    #1

    I0 = 0; I1 = 1; I2 = 0; I3 = 0; I4 = 0; I5 = 0; I6 = 0; I7 = 0;
    S0 = 0; S1 = 0; S2 = 0;
    #1
    S0 = 0; S1 = 0; S2 = 1;
    #1
    S0 = 0; S1 = 1; S2 = 0;
    #1
    S0 = 0; S1 = 1; S2 = 1;
    #1
    S0 = 1; S1 = 0; S2 = 0;
    #1
    S0 = 1; S1 = 0; S2 = 1;
    #1
    S0 = 1; S1 = 1; S2 = 0;
    #1
    S0 = 1; S1 = 1; S2 = 1;
    #1

    I0 = 0; I1 = 0; I2 = 1; I3 = 0; I4 = 0; I5 = 0; I6 = 0; I7 = 0;
    S0 = 0; S1 = 0; S2 = 0;
    #1
    S0 = 0; S1 = 0; S2 = 1;
    #1
    S0 = 0; S1 = 1; S2 = 0;
    #1
    S0 = 0; S1 = 1; S2 = 1;
    #1
    S0 = 1; S1 = 0; S2 = 0;
    #1
    S0 = 1; S1 = 0; S2 = 1;
    #1
    S0 = 1; S1 = 1; S2 = 0;
    #1
    S0 = 1; S1 = 1; S2 = 1;
    #1

    I0 = 0; I1 = 0; I2 = 0; I3 = 1; I4 = 0; I5 = 0; I6 = 0; I7 = 0;
    S0 = 0; S1 = 0; S2 = 0;
    #1
    S0 = 0; S1 = 0; S2 = 1;
    #1
    S0 = 0; S1 = 1; S2 = 0;
    #1
    S0 = 0; S1 = 1; S2 = 1;
    #1
    S0 = 1; S1 = 0; S2 = 0;
    #1
    S0 = 1; S1 = 0; S2 = 1;
    #1
    S0 = 1; S1 = 1; S2 = 0;
    #1
    S0 = 1; S1 = 1; S2 = 1;
    #1

    I0 = 0; I1 = 0; I2 = 0; I3 = 0; I4 = 1; I5 = 0; I6 = 0; I7 = 0;
    S0 = 0; S1 = 0; S2 = 0;
    #1
    S0 = 0; S1 = 0; S2 = 1;
    #1
    S0 = 0; S1 = 1; S2 = 0;
    #1
    S0 = 0; S1 = 1; S2 = 1;
    #1
    S0 = 1; S1 = 0; S2 = 0;
    #1
    S0 = 1; S1 = 0; S2 = 1;
    #1
    S0 = 1; S1 = 1; S2 = 0;
    #1
    S0 = 1; S1 = 1; S2 = 1;
    #1

    I0 = 0; I1 = 0; I2 = 0; I3 = 0; I4 = 0; I5 = 1; I6 = 0; I7 = 0;
    S0 = 0; S1 = 0; S2 = 0;
    #1
    S0 = 0; S1 = 0; S2 = 1;
    #1
    S0 = 0; S1 = 1; S2 = 0;
    #1
    S0 = 0; S1 = 1; S2 = 1;
    #1
    S0 = 1; S1 = 0; S2 = 0;
    #1
    S0 = 1; S1 = 0; S2 = 1;
    #1
    S0 = 1; S1 = 1; S2 = 0;
    #1
    S0 = 1; S1 = 1; S2 = 1;
    #1

    I0 = 0; I1 = 0; I2 = 0; I3 = 0; I4 = 0; I5 = 0; I6 = 1; I7 = 0;
    S0 = 0; S1 = 0; S2 = 0;
    #1
    S0 = 0; S1 = 0; S2 = 1;
    #1
    S0 = 0; S1 = 1; S2 = 0;
    #1
    S0 = 0; S1 = 1; S2 = 1;
    #1
    S0 = 1; S1 = 0; S2 = 0;
    #1
    S0 = 1; S1 = 0; S2 = 1;
    #1
    S0 = 1; S1 = 1; S2 = 0;
    #1
    S0 = 1; S1 = 1; S2 = 1;
    #1

    I0 = 0; I1 = 0; I2 = 0; I3 = 0; I4 = 0; I5 = 0; I6 = 0; I7 = 1;
    S0 = 0; S1 = 0; S2 = 0;
    #1
    S0 = 0; S1 = 0; S2 = 1;
    #1
    S0 = 0; S1 = 1; S2 = 0;
    #1
    S0 = 0; S1 = 1; S2 = 1;
    #1
    S0 = 1; S1 = 0; S2 = 0;
    #1
    S0 = 1; S1 = 0; S2 = 1;
    #1
    S0 = 1; S1 = 1; S2 = 0;
    #1
    S0 = 1; S1 = 1; S2 = 1;
    #1

    I0 = 1; I1 = 0; I2 = 0; I3 = 0; I4 = 0; I5 = 0; I6 = 0; I7 = 0;
    S0 = 0; S1 = 0; S2 = 0;
    #1
    S0 = 0; S1 = 0; S2 = 1;
    #1
    S0 = 0; S1 = 1; S2 = 0;
    #1
    S0 = 0; S1 = 1; S2 = 1;
    #1
    S0 = 1; S1 = 0; S2 = 0;
    #1
    S0 = 1; S1 = 0; S2 = 1;
    #1
    S0 = 1; S1 = 1; S2 = 0;
    #1
    S0 = 1; S1 = 1; S2 = 1;
    #1

    I0 = 0; I1 = 1; I2 = 0; I3 = 0; I4 = 0; I5 = 0; I6 = 0; I7 = 0;
    S0 = 0; S1 = 0; S2 = 0;
    #1
    S0 = 0; S1 = 0; S2 = 1;
    #1
    S0 = 0; S1 = 1; S2 = 0;
    #1
    S0 = 0; S1 = 1; S2 = 1;
    #1
    S0 = 1; S1 = 0; S2 = 0;
    #1
    S0 = 1; S1 = 0; S2 = 1;
    #1
    S0 = 1; S1 = 1; S2 = 0;
    #1
    S0 = 1; S1 = 1; S2 = 1;
    #1

    I0 = 0; I1 = 0; I2 = 1; I3 = 0; I4 = 0; I5 = 0; I6 = 0; I7 = 0;
    S0 = 0; S1 = 0; S2 = 0;
    #1
    S0 = 0; S1 = 0; S2 = 1;
    #1
    S0 = 0; S1 = 1; S2 = 0;
    #1
    S0 = 0; S1 = 1; S2 = 1;
    #1
    S0 = 1; S1 = 0; S2 = 0;
    #1
    S0 = 1; S1 = 0; S2 = 1;
    #1
    S0 = 1; S1 = 1; S2 = 0;
    #1
    S0 = 1; S1 = 1; S2 = 1;
    #1

    I0 = 0; I1 = 0; I2 = 0; I3 = 1; I4 = 0; I5 = 0; I6 = 0; I7 = 0;
    S0 = 0; S1 = 0; S2 = 0;
    #1
    S0 = 0; S1 = 0; S2 = 1;
    #1
    S0 = 0; S1 = 1; S2 = 0;
    #1
    S0 = 0; S1 = 1; S2 = 1;
    #1
    S0 = 1; S1 = 0; S2 = 0;
    #1
    S0 = 1; S1 = 0; S2 = 1;
    #1
    S0 = 1; S1 = 1; S2 = 0;
    #1
    S0 = 1; S1 = 1; S2 = 1;
    #1

    I0 = 0; I1 = 0; I2 = 0; I3 = 0; I4 = 1; I5 = 0; I6 = 0; I7 = 0;
    S0 = 0; S1 = 0; S2 = 0;
    #1
    S0 = 0; S1 = 0; S2 = 1;
    #1
    S0 = 0; S1 = 1; S2 = 0;
    #1
    S0 = 0; S1 = 1; S2 = 1;
    #1
    S0 = 1; S1 = 0; S2 = 0;
    #1
    S0 = 1; S1 = 0; S2 = 1;
    #1
    S0 = 1; S1 = 1; S2 = 0;
    #1
    S0 = 1; S1 = 1; S2 = 1;
    #1

    I0 = 0; I1 = 0; I2 = 0; I3 = 0; I4 = 0; I5 = 1; I6 = 0; I7 = 0;
    S0 = 0; S1 = 0; S2 = 0;
    #1
    S0 = 0; S1 = 0; S2 = 1;
    #1
    S0 = 0; S1 = 1; S2 = 0;
    #1
    S0 = 0; S1 = 1; S2 = 1;
    #1
    S0 = 1; S1 = 0; S2 = 0;
    #1
    S0 = 1; S1 = 0; S2 = 1;
    #1
    S0 = 1; S1 = 1; S2 = 0;
    #1
    S0 = 1; S1 = 1; S2 = 1;
    #1

    I0 = 0; I1 = 0; I2 = 0; I3 = 0; I4 = 0; I5 = 0; I6 = 1; I7 = 0;
    S0 = 0; S1 = 0; S2 = 0;
    #1
    S0 = 0; S1 = 0; S2 = 1;
    #1
    S0 = 0; S1 = 1; S2 = 0;
    #1
    S0 = 0; S1 = 1; S2 = 1;
    #1
    S0 = 1; S1 = 0; S2 = 0;
    #1
    S0 = 1; S1 = 0; S2 = 1;
    #1
    S0 = 1; S1 = 1; S2 = 0;
    #1
    S0 = 1; S1 = 1; S2 = 1;
    #1

    I0 = 0; I1 = 0; I2 = 0; I3 = 0; I4 = 0; I5 = 0; I6 = 0; I7 = 1;
    S0 = 0; S1 = 0; S2 = 0;
    #1
    S0 = 0; S1 = 0; S2 = 1;
    #1
    S0 = 0; S1 = 1; S2 = 0;
    #1
    S0 = 0; S1 = 1; S2 = 1;
    #1
    S0 = 1; S1 = 0; S2 = 0;
    #1
    S0 = 1; S1 = 0; S2 = 1;
    #1
    S0 = 1; S1 = 1; S2 = 0;
    #1
    S0 = 1; S1 = 1; S2 = 1;
    #1
	
	$display("test complete!");
end

endmodule

multiplexer/multiplexer.vcd
$date
	Mon Sep  9 10:14:40 2024
$end
$version
	Icarus Verilog
$end
$timescale
	1ns
$end
$scope module multiplexer_tb $end
$var wire 1 ! O0 $end
$var reg 1 " I0 $end
$var reg 1 # I1 $end
$var reg 1 $ I2 $end
$var reg 1 % I3 $end
$var reg 1 & I4 $end
$var reg 1 ' I5 $end
$var reg 1 ( I6 $end
$var reg 1 ) I7 $end
$var reg 1 * S0 $end
$var reg 1 + S1 $end
$var reg 1 , S2 $end
$scope module uut $end
$var wire 1 " I0 $end
$var wire 1 # I1 $end
$var wire 1 $ I2 $end
$var wire 1 % I3 $end
$var wire 1 & I4 $end
$var wire 1 ' I5 $end
$var wire 1 ( I6 $end
$var wire 1 ) I7 $end
$var wire 1 ! O0 $end
$var wire 1 * S0 $end
$var wire 1 + S1 $end
$var wire 1 , S2 $end
$var wire 1 - W0 $end
$var wire 1 . W1 $end
$var wire 1 / W2 $end
$var wire 1 0 W3 $end
$var wire 1 1 W4 $end
$var wire 1 2 W5 $end
$var wire 1 3 W6 $end
$var wire 1 4 W7 $end
$upscope $end
$upscope $end
$enddefinitions $end
$comment Show the parameter values. $end
$dumpall
$end
#0
$dumpvars
04
03
02
01
00
0/
0.
1-
0,
0+
0*
0)
0(
0'
0&
0%
0$
0#
1"
1!
$end
#1
0!
0-
1,
#2
0,
1+
#3
1,
#4
0,
0+
1*
#5
1,
#6
0,
1+
#7
1,
#8
0,
0+
0*
1#
0"
#9
1!
1.
1,
#10
0!
0.
0,
1+
#11
1,
#12
0,
0+
1*
#13
1,
#14
0,
1+
#15
1,
#16
0,
0+
0*
1$
0#
#17
1,
#18
1!
1/
0,
1+
#19
0!
0/
1,
#20
0,
0+
1*
#21
1,
#22
0,
1+
#23
1,
#24
0,
0+
0*
1%
0$
#25
1,
#26
0,
1+
#27
1!
10
1,
#28
0!
00
0,
0+
1*
#29
1,
#30
0,
1+
#31
1,
#32
0,
0+
0*
1&
0%
#33
1,
#34
0,
1+
#35
1,
#36
1!
11
0,
0+
1*
#37
0!
01
1,
#38
0,
1+
#39
1,
#40
0,
0+
0*
1'
0&
#41
1,
#42
0,
1+
#43
1,
#44
0,
0+
1*
#45
1!
12
1,
#46
0!
02
0,
1+
#47
1,
#48
0,
0+
0*
1(
0'
#49
1,
#50
0,
1+
#51
1,
#52
0,
0+
1*
#53
1,
#54
1!
13
0,
1+
#55
0!
03
1,
#56
0,
0+
0*
1)
0(
#57
1,
#58
0,
1+
#59
1,
#60
0,
0+
1*
#61
1,
#62
0,
1+
#63
1!
14
1,
#64
1!
1-
04
0,
0+
0*
0)
1"
#65
0!
0-
1,
#66
0,
1+
#67
1,
#68
0,
0+
1*
#69
1,
#70
0,
1+
#71
1,
#72
0,
0+
0*
1#
0"
#73
1!
1.
1,
#74
0!
0.
0,
1+
#75
1,
#76
0,
0+
1*
#77
1,
#78
0,
1+
#79
1,
#80
0,
0+
0*
1$
0#
#81
1,
#82
1!
1/
0,
1+
#83
0!
0/
1,
#84
0,
0+
1*
#85
1,
#86
0,
1+
#87
1,
#88
0,
0+
0*
1%
0$
#89
1,
#90
0,
1+
#91
1!
10
1,
#92
0!
00
0,
0+
1*
#93
1,
#94
0,
1+
#95
1,
#96
0,
0+
0*
1&
0%
#97
1,
#98
0,
1+
#99
1,
#100
1!
11
0,
0+
1*
#101
0!
01
1,
#102
0,
1+
#103
1,
#104
0,
0+
0*
1'
0&
#105
1,
#106
0,
1+
#107
1,
#108
0,
0+
1*
#109
1!
12
1,
#110
0!
02
0,
1+
#111
1,
#112
0,
0+
0*
1(
0'
#113
1,
#114
0,
1+
#115
1,
#116
0,
0+
1*
#117
1,
#118
1!
13
0,
1+
#119
0!
03
1,
#120
0,
0+
0*
1)
0(
#121
1,
#122
0,
1+
#123
1,
#124
0,
0+
1*
#125
1,
#126
0,
1+
#127
1!
14
1,
