incrementer/incrementer.v
module incrementer(I0, I1, I2, O0, O1, O2);

	input I0, I1, I2;
	output O0, O1, O2;

	wire W1, W2, W3;
	
	and(W1, I2, ~I1);
	and(W2, I2, ~I0);
	and(W3, ~I2, I1, I0);

	or(O2, W1, W2, W3);
	
	xor(O1, I0, I1);

	or(O0, ~I0, 0);

endmodule

incrementer/incrementer_tb.v
`timescale 1ns / 1ns

`include "incrementer.v"


module incrementer_tb;

reg I0, I1, I2;

wire O0, O1, O2;

incrementer uut(I2, I1, I0, O2, O1, O0);

initial begin
	$dumpfile("incrementer.vcd");
	$dumpvars(0, incrementer_tb);

	I0 = 0; I1 = 0; I2 = 0;
	#10
	I0 = 0; I1 = 0; I2 = 1;
	#10
	I0 = 0; I1 = 1; I2 = 0;
	#10
	I0 = 0; I1 = 1; I2 = 1;
	#10
	I0 = 1; I1 = 0; I2 = 0;
	#10
	I0 = 1; I1 = 0; I2 = 1;
	#10
	I0 = 1; I1 = 1; I2 = 0;
	#10
	I0 = 1; I1 = 1; I2 = 1;
	#10

	$display("test complete!");

end

endmodule

incrementer/incrementer.vcd
$date
	Mon Sep  9 10:57:09 2024
$end
$version
	Icarus Verilog
$end
$timescale
	1ns
$end
$scope module incrementer_tb $end
$var wire 1 ! O2 $end
$var wire 1 " O1 $end
$var wire 1 # O0 $end
$var reg 1 $ I0 $end
$var reg 1 % I1 $end
$var reg 1 & I2 $end
$scope module uut $end
$var wire 1 & I0 $end
$var wire 1 % I1 $end
$var wire 1 $ I2 $end
$var wire 1 ! O0 $end
$var wire 1 " O1 $end
$var wire 1 # O2 $end
$var wire 1 ' W1 $end
$var wire 1 ( W2 $end
$var wire 1 ) W3 $end
$upscope $end
$upscope $end
$enddefinitions $end
$comment Show the parameter values. $end
$dumpall
$end
#0
$dumpvars
0)
0(
0'
0&
0%
0$
0#
0"
1!
$end
#10
0!
1"
1&
#20
1!
0&
1%
#30
1#
0!
1)
0"
1&
#40
1(
1!
1'
1#
0)
0&
0%
1$
#50
0(
0!
1"
1&
#60
1(
1!
0'
0&
1%
#70
0#
0(
0!
0"
1&
