comparator/comparator.v
module comparator(A, B, C, D, E, F, G);

	input A, B, C, D, E, F;
	output G;

	wire W0, W1, W2, W3, W4, W6;

	and(W0, ~A, D);
	and(W1, ~A, ~B, E);
	and(W2, ~B, D, E);
	and(W3, ~A, ~B, ~C, F);
	and(W4, ~A, ~C, E, F);
	and(W5, ~B, ~C, D, F);
	and(W6, ~C, D, E, F);

	or(G, W0, W1, W2, W3, W4, W6);

endmodule;

comparator/comparator_tb.v
`timescale 1ns / 1ns

`include "comparator.v"

module comparator_tb;

reg A, B, C, D, E, F;

wire G;

comparator uut(A, B, C, D, E, F, G);

initial begin
	$dumpfile("comparator.vcd");
	$dumpvars(0, comparator_tb);
	
	A =  0;	B =  0;	C =  0;	D =  0;	E =  0;	F =  0;
	#1
	A =  0;	B =  0;	C =  0;	D =  0;	E =  0;	F =  1;
	#1
	A =  0;	B =  0;	C =  0;	D =  0;	E =  1;	F =  0;
	#1
	A =  0;	B =  0;	C =  0;	D =  0;	E =  1;	F =  1;
	#1
	A =  0;	B =  0;	C =  0;	D =  1;	E =  0;	F =  0;
	#1
	A =  0;	B =  0;	C =  0;	D =  1;	E =  0;	F =  1;
	#1
	A =  0;	B =  0;	C =  0;	D =  1;	E =  1;	F =  0;
	#1
	A =  0;	B =  0;	C =  0;	D =  1;	E =  1;	F =  1;
	#1
	A =  0;	B =  0;	C =  1;	D =  0;	E =  0;	F =  0;
	#1
	A =  0;	B =  0;	C =  1;	D =  0;	E =  0;	F =  1;
	#1
	A =  0;	B =  0;	C =  1;	D =  0;	E =  1;	F =  0;
	#1
	A =  0;	B =  0;	C =  1;	D =  0;	E =  1;	F =  1;
	#1
	A =  0;	B =  0;	C =  1;	D =  1;	E =  0;	F =  0;
	#1
	A =  0;	B =  0;	C =  1;	D =  1;	E =  0;	F =  1;
	#1
	A =  0;	B =  0;	C =  1;	D =  1;	E =  1;	F =  0;
	#1
	A =  0;	B =  0;	C =  1;	D =  1;	E =  1;	F =  1;
	#1
	A =  0;	B =  1;	C =  0;	D =  0;	E =  0;	F =  0;
	#1
	A =  0;	B =  1;	C =  0;	D =  0;	E =  0;	F =  1;
	#1
	A =  0;	B =  1;	C =  0;	D =  0;	E =  1;	F =  0;
	#1
	A =  0;	B =  1;	C =  0;	D =  0;	E =  1;	F =  1;
	#1
	A =  0;	B =  1;	C =  0;	D =  1;	E =  0;	F =  0;
	#1
	A =  0;	B =  1;	C =  0;	D =  1;	E =  0;	F =  1;
	#1
	A =  0;	B =  1;	C =  0;	D =  1;	E =  1;	F =  0;
	#1
	A =  0;	B =  1;	C =  0;	D =  1;	E =  1;	F =  1;
	#1
	A =  0;	B =  1;	C =  1;	D =  0;	E =  0;	F =  0;
	#1
	A =  0;	B =  1;	C =  1;	D =  0;	E =  0;	F =  1;
	#1
	A =  0;	B =  1;	C =  1;	D =  0;	E =  1;	F =  0;
	#1
	A =  0;	B =  1;	C =  1;	D =  0;	E =  1;	F =  1;
	#1
	A =  0;	B =  1;	C =  1;	D =  1;	E =  0;	F =  0;
	#1
	A =  0;	B =  1;	C =  1;	D =  1;	E =  0;	F =  1;
	#1
	A =  0;	B =  1;	C =  1;	D =  1;	E =  1;	F =  0;
	#1
	A =  0;	B =  1;	C =  1;	D =  1;	E =  1;	F =  1;
	#1
	A =  1;	B =  0;	C =  0;	D =  0;	E =  0;	F =  0;
	#1
	A =  1;	B =  0;	C =  0;	D =  0;	E =  0;	F =  1;
	#1
	A =  1;	B =  0;	C =  0;	D =  0;	E =  1;	F =  0;
	#1
	A =  1;	B =  0;	C =  0;	D =  0;	E =  1;	F =  1;
	#1
	A =  1;	B =  0;	C =  0;	D =  1;	E =  0;	F =  0;
	#1
	A =  1;	B =  0;	C =  0;	D =  1;	E =  0;	F =  1;
	#1
	A =  1;	B =  0;	C =  0;	D =  1;	E =  1;	F =  0;
	#1
	A =  1;	B =  0;	C =  0;	D =  1;	E =  1;	F =  1;
	#1
	A =  1;	B =  0;	C =  1;	D =  0;	E =  0;	F =  0;
	#1
	A =  1;	B =  0;	C =  1;	D =  0;	E =  0;	F =  1;
	#1
	A =  1;	B =  0;	C =  1;	D =  0;	E =  1;	F =  0;
	#1
	A =  1;	B =  0;	C =  1;	D =  0;	E =  1;	F =  1;
	#1
	A =  1;	B =  0;	C =  1;	D =  1;	E =  0;	F =  0;
	#1
	A =  1;	B =  0;	C =  1;	D =  1;	E =  0;	F =  1;
	#1
	A =  1;	B =  0;	C =  1;	D =  1;	E =  1;	F =  0;
	#1
	A =  1;	B =  0;	C =  1;	D =  1;	E =  1;	F =  1;
	#1
	A =  1;	B =  1;	C =  0;	D =  0;	E =  0;	F =  0;
	#1
	A =  1;	B =  1;	C =  0;	D =  0;	E =  0;	F =  1;
	#1
	A =  1;	B =  1;	C =  0;	D =  0;	E =  1;	F =  0;
	#1
	A =  1;	B =  1;	C =  0;	D =  0;	E =  1;	F =  1;
	#1
	A =  1;	B =  1;	C =  0;	D =  1;	E =  0;	F =  0;
	#1
	A =  1;	B =  1;	C =  0;	D =  1;	E =  0;	F =  1;
	#1
	A =  1;	B =  1;	C =  0;	D =  1;	E =  1;	F =  0;
	#1
	A =  1;	B =  1;	C =  0;	D =  1;	E =  1;	F =  1;
	#1
	A =  1;	B =  1;	C =  1;	D =  0;	E =  0;	F =  0;
	#1
	A =  1;	B =  1;	C =  1;	D =  0;	E =  0;	F =  1;
	#1
	A =  1;	B =  1;	C =  1;	D =  0;	E =  1;	F =  0;
	#1
	A =  1;	B =  1;	C =  1;	D =  0;	E =  1;	F =  1;
	#1
	A =  1;	B =  1;	C =  1;	D =  1;	E =  0;	F =  0;
	#1
	A =  1;	B =  1;	C =  1;	D =  1;	E =  0;	F =  1;
	#1
	A =  1;	B =  1;	C =  1;	D =  1;	E =  1;	F =  0;
	#1
	A =  1;	B =  1;	C =  1;	D =  1;	E =  1;	F =  1;
	#1	
	$display("test complete!");
end

endmodule

comparator/comparator.vcd
$date
	Mon Sep  9 11:35:47 2024
$end
$version
	Icarus Verilog
$end
$timescale
	1ns
$end
$scope module comparator_tb $end
$var wire 1 ! G $end
$var reg 1 " A $end
$var reg 1 # B $end
$var reg 1 $ C $end
$var reg 1 % D $end
$var reg 1 & E $end
$var reg 1 ' F $end
$scope module uut $end
$var wire 1 " A $end
$var wire 1 # B $end
$var wire 1 $ C $end
$var wire 1 % D $end
$var wire 1 & E $end
$var wire 1 ' F $end
$var wire 1 ! G $end
$var wire 1 ( W0 $end
$var wire 1 ) W1 $end
$var wire 1 * W2 $end
$var wire 1 + W3 $end
$var wire 1 , W4 $end
$var wire 1 - W5 $end
$var wire 1 . W6 $end
$upscope $end
$upscope $end
$enddefinitions $end
$comment Show the parameter values. $end
$dumpall
$end
#0
$dumpvars
0.
0-
0,
0+
0*
0)
0(
0'
0&
0%
0$
0#
0"
0!
$end
#1
1!
1+
1'
#2
0+
1)
0'
1&
#3
1+
1,
1'
#4
0+
0)
0,
1(
0'
0&
1%
#5
1+
1-
1'
#6
0+
0-
1)
1*
0'
1&
#7
1+
1,
1-
1.
1'
#8
0!
0+
0)
0,
0(
0*
0-
0.
0'
0&
0%
1$
#9
1'
#10
1!
1)
0'
1&
#11
1'
#12
0)
1(
0'
0&
1%
#13
1'
#14
1)
1*
0'
1&
#15
1'
#16
0!
0)
0(
0*
0'
0&
0%
0$
1#
#17
1'
#18
0'
1&
#19
1!
1,
1'
#20
0,
1(
0'
0&
1%
#21
1'
#22
0'
1&
#23
1,
1.
1'
#24
0!
0,
0(
0.
0'
0&
0%
1$
#25
1'
#26
0'
1&
#27
1'
#28
1!
1(
0'
0&
1%
#29
1'
#30
0'
1&
#31
1'
#32
0!
0(
0'
0&
0%
0$
0#
1"
#33
1'
#34
0'
1&
#35
1'
#36
0'
0&
1%
#37
1-
1'
#38
1!
0-
1*
0'
1&
#39
1-
1.
1'
#40
0!
0*
0-
0.
0'
0&
0%
1$
#41
1'
#42
0'
1&
#43
1'
#44
0'
0&
1%
#45
1'
#46
1!
1*
0'
1&
#47
1'
#48
0!
0*
0'
0&
0%
0$
1#
#49
1'
#50
0'
1&
#51
1'
#52
0'
0&
1%
#53
1'
#54
0'
1&
#55
1!
1.
1'
#56
0!
0.
0'
0&
0%
1$
#57
1'
#58
0'
1&
#59
1'
#60
0'
0&
1%
#61
1'
#62
0'
1&
#63
1'
